assets/output.svg
lexz/LexZ.py
lexz/__init__.py
lexz/__main__.py
lexz/alias_backend/__main__.py
lexz/alias_backend/backend.py
lexz/alias_backend/default.py
lexz/exceptions.py
lexz/tree_variabel.py
lexz-0.1.2.dist-info/LICENSE
lexz-0.1.2.dist-info/METADATA
lexz-0.1.2.dist-info/WHEEL
lexz-0.1.2.dist-info/RECORD
