Metadata-Version: 2.1
Name: lexz
Version: 0.1.2
Summary: Time traveler for obfuscation or another purpose
License: Apache-2.0
Author: krypton-byte
Author-email: rosid6434@gmail.com
Requires-Python: >=3.11,<4.0
Classifier: License :: OSI Approved :: Apache Software License
Classifier: Programming Language :: Python :: 3
Classifier: Programming Language :: Python :: 3.11
